[
  {
    "orderNo": "6EAECA0F",
    "orderDate": "2023-11-15",
    "orderStatus": "INVALID",
    "orderValidationCode": "CARD_NUMBER_INVALID",
    "priceTotalInPence": 2400,
    "pizzasInOrder": [
      {
        "name": "R3: Super Cheese",
        "priceInPence": 1400
      },
      {
        "name": "R3: All Shrooms",
        "priceInPence": 900
      }
    ],
    "creditCardInformation": {
      "creditCardNumber": "481",
      "creditCardExpiry": "07/27",
      "cvv": "107"
    }
  },
  {
    "orderNo": "3788C49D",
    "orderDate": "2023-11-15",
    "orderStatus": "INVALID",
    "orderValidationCode": "EXPIRY_DATE_INVALID",
    "priceTotalInPence": 2400,
    "pizzasInOrder": [
      {
        "name": "R4: Proper Pizza",
        "priceInPence": 1400
      },
      {
        "name": "R4: Pineapple \u0026 Ham \u0026 Cheese",
        "priceInPence": 900
      }
    ],
    "creditCardInformation": {
      "creditCardNumber": "5354095417871382",
      "creditCardExpiry": "14/12",
      "cvv": "391"
    }
  },
  {
    "orderNo": "676E47C3",
    "orderDate": "2023-11-15",
    "orderStatus": "INVALID",
    "orderValidationCode": "CVV_INVALID",
    "priceTotalInPence": 2400,
    "pizzasInOrder": [
      {
        "name": "R6: Sucuk delight",
        "priceInPence": 1400
      },
      {
        "name": "R6: Dreams of Syria",
        "priceInPence": 900
      }
    ],
    "creditCardInformation": {
      "creditCardNumber": "5143005921274540",
      "creditCardExpiry": "10/26",
      "cvv": "4798"
    }
  },
  {
    "orderNo": "0A45466D",
    "orderDate": "2023-11-15",
    "orderStatus": "INVALID",
    "orderValidationCode": "TOTAL_INCORRECT",
    "priceTotalInPence": 3398,
    "pizzasInOrder": [
      {
        "name": "R2: Meat Lover",
        "priceInPence": 1400
      },
      {
        "name": "R2: Vegan Delight",
        "priceInPence": 1100
      }
    ],
    "creditCardInformation": {
      "creditCardNumber": "4871731218903993",
      "creditCardExpiry": "02/25",
      "cvv": "593"
    }
  },
  {
    "orderNo": "57F1EA87",
    "orderDate": "2023-11-15",
    "orderStatus": "INVALID",
    "orderValidationCode": "PIZZA_NOT_DEFINED",
    "priceTotalInPence": 498705480,
    "pizzasInOrder": [
      {
        "name": "R2: Meat Lover",
        "priceInPence": 1400
      },
      {
        "name": "R2: Vegan Delight",
        "priceInPence": 1100
      },
      {
        "name": "Pizza-Surprise ",
        "priceInPence": 498702880
      }
    ],
    "creditCardInformation": {
      "creditCardNumber": "4861618560796582",
      "creditCardExpiry": "07/28",
      "cvv": "284"
    }
  },
  {
    "orderNo": "21DF8668",
    "orderDate": "2023-11-15",
    "orderStatus": "INVALID",
    "orderValidationCode": "MAX_PIZZA_COUNT_EXCEEDED",
    "priceTotalInPence": 8200,
    "pizzasInOrder": [
      {
        "name": "R2: Meat Lover",
        "priceInPence": 1400
      },
      {
        "name": "R2: Vegan Delight",
        "priceInPence": 1100
      },
      {
        "name": "R2: Meat Lover",
        "priceInPence": 1400
      },
      {
        "name": "R2: Meat Lover",
        "priceInPence": 1400
      },
      {
        "name": "R2: Meat Lover",
        "priceInPence": 1400
      },
      {
        "name": "R2: Meat Lover",
        "priceInPence": 1400
      }
    ],
    "creditCardInformation": {
      "creditCardNumber": "4421910329444064",
      "creditCardExpiry": "02/28",
      "cvv": "108"
    }
  },
  {
    "orderNo": "22178F41",
    "orderDate": "2023-11-15",
    "orderStatus": "INVALID",
    "orderValidationCode": "PIZZA_FROM_MULTIPLE_RESTAURANTS",
    "priceTotalInPence": 4000,
    "pizzasInOrder": [
      {
        "name": "R2: Meat Lover",
        "priceInPence": 1400
      },
      {
        "name": "R2: Vegan Delight",
        "priceInPence": 1100
      },
      {
        "name": "R3: Super Cheese",
        "priceInPence": 1400
      }
    ],
    "creditCardInformation": {
      "creditCardNumber": "5445758237505941",
      "creditCardExpiry": "10/25",
      "cvv": "383"
    }
  },
  {
    "orderNo": "37BD18C8",
    "orderDate": "2023-11-15",
    "orderStatus": "INVALID",
    "orderValidationCode": "RESTAURANT_CLOSED",
    "priceTotalInPence": 1100,
    "pizzasInOrder": [
      {
        "name": "R1: Margarita",
        "priceInPence": 1000
      }
    ],
    "creditCardInformation": {
      "creditCardNumber": "4705247761065082",
      "creditCardExpiry": "05/25",
      "cvv": "217"
    }
  },
  {
    "orderNo": "31B4A08B",
    "orderDate": "2023-11-15",
    "orderStatus": "DELIVERED",
    "orderValidationCode": "NO_ERROR",
    "priceTotalInPence": 2600,
    "pizzasInOrder": [
      {
        "name": "R2: Meat Lover",
        "priceInPence": 1400
      },
      {
        "name": "R2: Vegan Delight",
        "priceInPence": 1100
      }
    ],
    "creditCardInformation": {
      "creditCardNumber": "2720765488196612",
      "creditCardExpiry": "06/24",
      "cvv": "994"
    }
  },
  {
    "orderNo": "0937DBD9",
    "orderDate": "2023-11-15",
    "orderStatus": "DELIVERED",
    "orderValidationCode": "NO_ERROR",
    "priceTotalInPence": 2400,
    "pizzasInOrder": [
      {
        "name": "R3: Super Cheese",
        "priceInPence": 1400
      },
      {
        "name": "R3: All Shrooms",
        "priceInPence": 900
      }
    ],
    "creditCardInformation": {
      "creditCardNumber": "5311426360341549",
      "creditCardExpiry": "03/27",
      "cvv": "195"
    }
  },
  {
    "orderNo": "15C0F39C",
    "orderDate": "2023-11-15",
    "orderStatus": "DELIVERED",
    "orderValidationCode": "NO_ERROR",
    "priceTotalInPence": 2400,
    "pizzasInOrder": [
      {
        "name": "R4: Proper Pizza",
        "priceInPence": 1400
      },
      {
        "name": "R4: Pineapple \u0026 Ham \u0026 Cheese",
        "priceInPence": 900
      }
    ],
    "creditCardInformation": {
      "creditCardNumber": "4872920410846246",
      "creditCardExpiry": "01/28",
      "cvv": "349"
    }
  },
  {
    "orderNo": "3BD8AAC0",
    "orderDate": "2023-11-15",
    "orderStatus": "DELIVERED",
    "orderValidationCode": "NO_ERROR",
    "priceTotalInPence": 2400,
    "pizzasInOrder": [
      {
        "name": "R6: Sucuk delight",
        "priceInPence": 1400
      },
      {
        "name": "R6: Dreams of Syria",
        "priceInPence": 900
      }
    ],
    "creditCardInformation": {
      "creditCardNumber": "4737263771441389",
      "creditCardExpiry": "10/26",
      "cvv": "160"
    }
  },
  {
    "orderNo": "0E1F7D4A",
    "orderDate": "2023-11-15",
    "orderStatus": "DELIVERED",
    "orderValidationCode": "NO_ERROR",
    "priceTotalInPence": 2600,
    "pizzasInOrder": [
      {
        "name": "R2: Meat Lover",
        "priceInPence": 1400
      },
      {
        "name": "R2: Vegan Delight",
        "priceInPence": 1100
      }
    ],
    "creditCardInformation": {
      "creditCardNumber": "4008605362228066",
      "creditCardExpiry": "07/27",
      "cvv": "189"
    }
  },
  {
    "orderNo": "538D7E82",
    "orderDate": "2023-11-15",
    "orderStatus": "DELIVERED",
    "orderValidationCode": "NO_ERROR",
    "priceTotalInPence": 2400,
    "pizzasInOrder": [
      {
        "name": "R3: Super Cheese",
        "priceInPence": 1400
      },
      {
        "name": "R3: All Shrooms",
        "priceInPence": 900
      }
    ],
    "creditCardInformation": {
      "creditCardNumber": "4390587245222977",
      "creditCardExpiry": "05/25",
      "cvv": "407"
    }
  },
  {
    "orderNo": "06E0A9F4",
    "orderDate": "2023-11-15",
    "orderStatus": "DELIVERED",
    "orderValidationCode": "NO_ERROR",
    "priceTotalInPence": 2400,
    "pizzasInOrder": [
      {
        "name": "R4: Proper Pizza",
        "priceInPence": 1400
      },
      {
        "name": "R4: Pineapple \u0026 Ham \u0026 Cheese",
        "priceInPence": 900
      }
    ],
    "creditCardInformation": {
      "creditCardNumber": "5512234597719447",
      "creditCardExpiry": "07/26",
      "cvv": "868"
    }
  },
  {
    "orderNo": "3F166B42",
    "orderDate": "2023-11-15",
    "orderStatus": "DELIVERED",
    "orderValidationCode": "NO_ERROR",
    "priceTotalInPence": 2400,
    "pizzasInOrder": [
      {
        "name": "R6: Sucuk delight",
        "priceInPence": 1400
      },
      {
        "name": "R6: Dreams of Syria",
        "priceInPence": 900
      }
    ],
    "creditCardInformation": {
      "creditCardNumber": "4354145822125461",
      "creditCardExpiry": "02/27",
      "cvv": "828"
    }
  },
  {
    "orderNo": "0D834A1D",
    "orderDate": "2023-11-15",
    "orderStatus": "DELIVERED",
    "orderValidationCode": "NO_ERROR",
    "priceTotalInPence": 2600,
    "pizzasInOrder": [
      {
        "name": "R2: Meat Lover",
        "priceInPence": 1400
      },
      {
        "name": "R2: Vegan Delight",
        "priceInPence": 1100
      }
    ],
    "creditCardInformation": {
      "creditCardNumber": "2720023522456158",
      "creditCardExpiry": "11/24",
      "cvv": "166"
    }
  },
  {
    "orderNo": "4A730114",
    "orderDate": "2023-11-15",
    "orderStatus": "DELIVERED",
    "orderValidationCode": "NO_ERROR",
    "priceTotalInPence": 2400,
    "pizzasInOrder": [
      {
        "name": "R3: Super Cheese",
        "priceInPence": 1400
      },
      {
        "name": "R3: All Shrooms",
        "priceInPence": 900
      }
    ],
    "creditCardInformation": {
      "creditCardNumber": "4658626830128087",
      "creditCardExpiry": "03/25",
      "cvv": "529"
    }
  },
  {
    "orderNo": "4C14E4FD",
    "orderDate": "2023-11-15",
    "orderStatus": "DELIVERED",
    "orderValidationCode": "NO_ERROR",
    "priceTotalInPence": 2400,
    "pizzasInOrder": [
      {
        "name": "R4: Proper Pizza",
        "priceInPence": 1400
      },
      {
        "name": "R4: Pineapple \u0026 Ham \u0026 Cheese",
        "priceInPence": 900
      }
    ],
    "creditCardInformation": {
      "creditCardNumber": "4573168857614121",
      "creditCardExpiry": "04/25",
      "cvv": "601"
    }
  },
  {
    "orderNo": "4160685C",
    "orderDate": "2023-11-15",
    "orderStatus": "DELIVERED",
    "orderValidationCode": "NO_ERROR",
    "priceTotalInPence": 2400,
    "pizzasInOrder": [
      {
        "name": "R6: Sucuk delight",
        "priceInPence": 1400
      },
      {
        "name": "R6: Dreams of Syria",
        "priceInPence": 900
      }
    ],
    "creditCardInformation": {
      "creditCardNumber": "5519282378313271",
      "creditCardExpiry": "08/25",
      "cvv": "784"
    }
  },
  {
    "orderNo": "65D2A540",
    "orderDate": "2023-11-15",
    "orderStatus": "DELIVERED",
    "orderValidationCode": "NO_ERROR",
    "priceTotalInPence": 2600,
    "pizzasInOrder": [
      {
        "name": "R2: Meat Lover",
        "priceInPence": 1400
      },
      {
        "name": "R2: Vegan Delight",
        "priceInPence": 1100
      }
    ],
    "creditCardInformation": {
      "creditCardNumber": "5425099997319254",
      "creditCardExpiry": "02/25",
      "cvv": "304"
    }
  },
  {
    "orderNo": "52A60A4D",
    "orderDate": "2023-11-15",
    "orderStatus": "DELIVERED",
    "orderValidationCode": "NO_ERROR",
    "priceTotalInPence": 2400,
    "pizzasInOrder": [
      {
        "name": "R3: Super Cheese",
        "priceInPence": 1400
      },
      {
        "name": "R3: All Shrooms",
        "priceInPence": 900
      }
    ],
    "creditCardInformation": {
      "creditCardNumber": "2221305348328487",
      "creditCardExpiry": "10/28",
      "cvv": "500"
    }
  },
  {
    "orderNo": "0A807FDF",
    "orderDate": "2023-11-15",
    "orderStatus": "DELIVERED",
    "orderValidationCode": "NO_ERROR",
    "priceTotalInPence": 2400,
    "pizzasInOrder": [
      {
        "name": "R4: Proper Pizza",
        "priceInPence": 1400
      },
      {
        "name": "R4: Pineapple \u0026 Ham \u0026 Cheese",
        "priceInPence": 900
      }
    ],
    "creditCardInformation": {
      "creditCardNumber": "4056653768525298",
      "creditCardExpiry": "07/24",
      "cvv": "997"
    }
  },
  {
    "orderNo": "6F4F3C19",
    "orderDate": "2023-11-15",
    "orderStatus": "DELIVERED",
    "orderValidationCode": "NO_ERROR",
    "priceTotalInPence": 2400,
    "pizzasInOrder": [
      {
        "name": "R6: Sucuk delight",
        "priceInPence": 1400
      },
      {
        "name": "R6: Dreams of Syria",
        "priceInPence": 900
      }
    ],
    "creditCardInformation": {
      "creditCardNumber": "5244654773713721",
      "creditCardExpiry": "04/24",
      "cvv": "944"
    }
  },
  {
    "orderNo": "1FD63331",
    "orderDate": "2023-11-15",
    "orderStatus": "DELIVERED",
    "orderValidationCode": "NO_ERROR",
    "priceTotalInPence": 2600,
    "pizzasInOrder": [
      {
        "name": "R2: Meat Lover",
        "priceInPence": 1400
      },
      {
        "name": "R2: Vegan Delight",
        "priceInPence": 1100
      }
    ],
    "creditCardInformation": {
      "creditCardNumber": "4566055500669363",
      "creditCardExpiry": "11/24",
      "cvv": "465"
    }
  },
  {
    "orderNo": "68904EE6",
    "orderDate": "2023-11-15",
    "orderStatus": "DELIVERED",
    "orderValidationCode": "NO_ERROR",
    "priceTotalInPence": 2400,
    "pizzasInOrder": [
      {
        "name": "R3: Super Cheese",
        "priceInPence": 1400
      },
      {
        "name": "R3: All Shrooms",
        "priceInPence": 900
      }
    ],
    "creditCardInformation": {
      "creditCardNumber": "4415714640621972",
      "creditCardExpiry": "03/28",
      "cvv": "369"
    }
  },
  {
    "orderNo": "36CC73FC",
    "orderDate": "2023-11-15",
    "orderStatus": "DELIVERED",
    "orderValidationCode": "NO_ERROR",
    "priceTotalInPence": 2400,
    "pizzasInOrder": [
      {
        "name": "R4: Proper Pizza",
        "priceInPence": 1400
      },
      {
        "name": "R4: Pineapple \u0026 Ham \u0026 Cheese",
        "priceInPence": 900
      }
    ],
    "creditCardInformation": {
      "creditCardNumber": "5110393570409131",
      "creditCardExpiry": "09/28",
      "cvv": "974"
    }
  },
  {
    "orderNo": "1495A896",
    "orderDate": "2023-11-15",
    "orderStatus": "DELIVERED",
    "orderValidationCode": "NO_ERROR",
    "priceTotalInPence": 2400,
    "pizzasInOrder": [
      {
        "name": "R6: Sucuk delight",
        "priceInPence": 1400
      },
      {
        "name": "R6: Dreams of Syria",
        "priceInPence": 900
      }
    ],
    "creditCardInformation": {
      "creditCardNumber": "5121470042513976",
      "creditCardExpiry": "06/26",
      "cvv": "946"
    }
  },
  {
    "orderNo": "2C84975D",
    "orderDate": "2023-11-15",
    "orderStatus": "DELIVERED",
    "orderValidationCode": "NO_ERROR",
    "priceTotalInPence": 2600,
    "pizzasInOrder": [
      {
        "name": "R2: Meat Lover",
        "priceInPence": 1400
      },
      {
        "name": "R2: Vegan Delight",
        "priceInPence": 1100
      }
    ],
    "creditCardInformation": {
      "creditCardNumber": "4658763834736803",
      "creditCardExpiry": "04/24",
      "cvv": "751"
    }
  },
  {
    "orderNo": "600D9559",
    "orderDate": "2023-11-15",
    "orderStatus": "DELIVERED",
    "orderValidationCode": "NO_ERROR",
    "priceTotalInPence": 2400,
    "pizzasInOrder": [
      {
        "name": "R3: Super Cheese",
        "priceInPence": 1400
      },
      {
        "name": "R3: All Shrooms",
        "priceInPence": 900
      }
    ],
    "creditCardInformation": {
      "creditCardNumber": "5442464794373905",
      "creditCardExpiry": "10/25",
      "cvv": "561"
    }
  },
  {
    "orderNo": "6F1C9830",
    "orderDate": "2023-11-15",
    "orderStatus": "DELIVERED",
    "orderValidationCode": "NO_ERROR",
    "priceTotalInPence": 2400,
    "pizzasInOrder": [
      {
        "name": "R4: Proper Pizza",
        "priceInPence": 1400
      },
      {
        "name": "R4: Pineapple \u0026 Ham \u0026 Cheese",
        "priceInPence": 900
      }
    ],
    "creditCardInformation": {
      "creditCardNumber": "5537801245414521",
      "creditCardExpiry": "07/26",
      "cvv": "403"
    }
  },
  {
    "orderNo": "506CD376",
    "orderDate": "2023-11-15",
    "orderStatus": "DELIVERED",
    "orderValidationCode": "NO_ERROR",
    "priceTotalInPence": 2400,
    "pizzasInOrder": [
      {
        "name": "R6: Sucuk delight",
        "priceInPence": 1400
      },
      {
        "name": "R6: Dreams of Syria",
        "priceInPence": 900
      }
    ],
    "creditCardInformation": {
      "creditCardNumber": "4538076168555574",
      "creditCardExpiry": "10/24",
      "cvv": "917"
    }
  },
  {
    "orderNo": "1A8E09CE",
    "orderDate": "2023-11-15",
    "orderStatus": "DELIVERED",
    "orderValidationCode": "NO_ERROR",
    "priceTotalInPence": 2600,
    "pizzasInOrder": [
      {
        "name": "R2: Meat Lover",
        "priceInPence": 1400
      },
      {
        "name": "R2: Vegan Delight",
        "priceInPence": 1100
      }
    ],
    "creditCardInformation": {
      "creditCardNumber": "5581327192802067",
      "creditCardExpiry": "05/28",
      "cvv": "717"
    }
  },
  {
    "orderNo": "6617A184",
    "orderDate": "2023-11-15",
    "orderStatus": "DELIVERED",
    "orderValidationCode": "NO_ERROR",
    "priceTotalInPence": 2400,
    "pizzasInOrder": [
      {
        "name": "R3: Super Cheese",
        "priceInPence": 1400
      },
      {
        "name": "R3: All Shrooms",
        "priceInPence": 900
      }
    ],
    "creditCardInformation": {
      "creditCardNumber": "4587184388812989",
      "creditCardExpiry": "08/24",
      "cvv": "958"
    }
  },
  {
    "orderNo": "26766F70",
    "orderDate": "2023-11-15",
    "orderStatus": "DELIVERED",
    "orderValidationCode": "NO_ERROR",
    "priceTotalInPence": 2400,
    "pizzasInOrder": [
      {
        "name": "R4: Proper Pizza",
        "priceInPence": 1400
      },
      {
        "name": "R4: Pineapple \u0026 Ham \u0026 Cheese",
        "priceInPence": 900
      }
    ],
    "creditCardInformation": {
      "creditCardNumber": "5411166332702027",
      "creditCardExpiry": "02/25",
      "cvv": "130"
    }
  },
  {
    "orderNo": "42D45256",
    "orderDate": "2023-11-15",
    "orderStatus": "DELIVERED",
    "orderValidationCode": "NO_ERROR",
    "priceTotalInPence": 2400,
    "pizzasInOrder": [
      {
        "name": "R6: Sucuk delight",
        "priceInPence": 1400
      },
      {
        "name": "R6: Dreams of Syria",
        "priceInPence": 900
      }
    ],
    "creditCardInformation": {
      "creditCardNumber": "5535211373597612",
      "creditCardExpiry": "08/26",
      "cvv": "816"
    }
  },
  {
    "orderNo": "27B3ABFB",
    "orderDate": "2023-11-15",
    "orderStatus": "DELIVERED",
    "orderValidationCode": "NO_ERROR",
    "priceTotalInPence": 2600,
    "pizzasInOrder": [
      {
        "name": "R2: Meat Lover",
        "priceInPence": 1400
      },
      {
        "name": "R2: Vegan Delight",
        "priceInPence": 1100
      }
    ],
    "creditCardInformation": {
      "creditCardNumber": "4893619611879031",
      "creditCardExpiry": "09/27",
      "cvv": "689"
    }
  },
  {
    "orderNo": "039941B0",
    "orderDate": "2023-11-15",
    "orderStatus": "DELIVERED",
    "orderValidationCode": "NO_ERROR",
    "priceTotalInPence": 2400,
    "pizzasInOrder": [
      {
        "name": "R3: Super Cheese",
        "priceInPence": 1400
      },
      {
        "name": "R3: All Shrooms",
        "priceInPence": 900
      }
    ],
    "creditCardInformation": {
      "creditCardNumber": "5389144272909645",
      "creditCardExpiry": "09/28",
      "cvv": "401"
    }
  },
  {
    "orderNo": "416E56F4",
    "orderDate": "2023-11-15",
    "orderStatus": "DELIVERED",
    "orderValidationCode": "NO_ERROR",
    "priceTotalInPence": 2400,
    "pizzasInOrder": [
      {
        "name": "R4: Proper Pizza",
        "priceInPence": 1400
      },
      {
        "name": "R4: Pineapple \u0026 Ham \u0026 Cheese",
        "priceInPence": 900
      }
    ],
    "creditCardInformation": {
      "creditCardNumber": "4666548341506769",
      "creditCardExpiry": "04/26",
      "cvv": "561"
    }
  },
  {
    "orderNo": "29163095",
    "orderDate": "2023-11-15",
    "orderStatus": "DELIVERED",
    "orderValidationCode": "NO_ERROR",
    "priceTotalInPence": 2400,
    "pizzasInOrder": [
      {
        "name": "R6: Sucuk delight",
        "priceInPence": 1400
      },
      {
        "name": "R6: Dreams of Syria",
        "priceInPence": 900
      }
    ],
    "creditCardInformation": {
      "creditCardNumber": "4704358410452174",
      "creditCardExpiry": "09/27",
      "cvv": "560"
    }
  },
  {
    "orderNo": "61F95723",
    "orderDate": "2023-11-15",
    "orderStatus": "DELIVERED",
    "orderValidationCode": "NO_ERROR",
    "priceTotalInPence": 2600,
    "pizzasInOrder": [
      {
        "name": "R2: Meat Lover",
        "priceInPence": 1400
      },
      {
        "name": "R2: Vegan Delight",
        "priceInPence": 1100
      }
    ],
    "creditCardInformation": {
      "creditCardNumber": "5394765737390071",
      "creditCardExpiry": "05/28",
      "cvv": "468"
    }
  },
  {
    "orderNo": "53FC945B",
    "orderDate": "2023-11-15",
    "orderStatus": "DELIVERED",
    "orderValidationCode": "NO_ERROR",
    "priceTotalInPence": 2400,
    "pizzasInOrder": [
      {
        "name": "R3: Super Cheese",
        "priceInPence": 1400
      },
      {
        "name": "R3: All Shrooms",
        "priceInPence": 900
      }
    ],
    "creditCardInformation": {
      "creditCardNumber": "5132455388040202",
      "creditCardExpiry": "02/27",
      "cvv": "665"
    }
  },
  {
    "orderNo": "2F82DEE8",
    "orderDate": "2023-11-15",
    "orderStatus": "DELIVERED",
    "orderValidationCode": "NO_ERROR",
    "priceTotalInPence": 2400,
    "pizzasInOrder": [
      {
        "name": "R4: Proper Pizza",
        "priceInPence": 1400
      },
      {
        "name": "R4: Pineapple \u0026 Ham \u0026 Cheese",
        "priceInPence": 900
      }
    ],
    "creditCardInformation": {
      "creditCardNumber": "5177381487158982",
      "creditCardExpiry": "01/25",
      "cvv": "044"
    }
  },
  {
    "orderNo": "40FCE423",
    "orderDate": "2023-11-15",
    "orderStatus": "DELIVERED",
    "orderValidationCode": "NO_ERROR",
    "priceTotalInPence": 2400,
    "pizzasInOrder": [
      {
        "name": "R6: Sucuk delight",
        "priceInPence": 1400
      },
      {
        "name": "R6: Dreams of Syria",
        "priceInPence": 900
      }
    ],
    "creditCardInformation": {
      "creditCardNumber": "4879921211797227",
      "creditCardExpiry": "04/27",
      "cvv": "563"
    }
  },
  {
    "orderNo": "33C49BCA",
    "orderDate": "2023-11-15",
    "orderStatus": "DELIVERED",
    "orderValidationCode": "NO_ERROR",
    "priceTotalInPence": 2600,
    "pizzasInOrder": [
      {
        "name": "R2: Meat Lover",
        "priceInPence": 1400
      },
      {
        "name": "R2: Vegan Delight",
        "priceInPence": 1100
      }
    ],
    "creditCardInformation": {
      "creditCardNumber": "4076599730992031",
      "creditCardExpiry": "01/26",
      "cvv": "588"
    }
  },
  {
    "orderNo": "52B2006B",
    "orderDate": "2023-11-15",
    "orderStatus": "DELIVERED",
    "orderValidationCode": "NO_ERROR",
    "priceTotalInPence": 2400,
    "pizzasInOrder": [
      {
        "name": "R3: Super Cheese",
        "priceInPence": 1400
      },
      {
        "name": "R3: All Shrooms",
        "priceInPence": 900
      }
    ],
    "creditCardInformation": {
      "creditCardNumber": "5514768167309392",
      "creditCardExpiry": "07/28",
      "cvv": "894"
    }
  },
  {
    "orderNo": "1E5F12A3",
    "orderDate": "2023-11-15",
    "orderStatus": "DELIVERED",
    "orderValidationCode": "NO_ERROR",
    "priceTotalInPence": 2400,
    "pizzasInOrder": [
      {
        "name": "R4: Proper Pizza",
        "priceInPence": 1400
      },
      {
        "name": "R4: Pineapple \u0026 Ham \u0026 Cheese",
        "priceInPence": 900
      }
    ],
    "creditCardInformation": {
      "creditCardNumber": "4594325640909318",
      "creditCardExpiry": "06/28",
      "cvv": "627"
    }
  },
  {
    "orderNo": "68287E23",
    "orderDate": "2023-11-15",
    "orderStatus": "DELIVERED",
    "orderValidationCode": "NO_ERROR",
    "priceTotalInPence": 2400,
    "pizzasInOrder": [
      {
        "name": "R6: Sucuk delight",
        "priceInPence": 1400
      },
      {
        "name": "R6: Dreams of Syria",
        "priceInPence": 900
      }
    ],
    "creditCardInformation": {
      "creditCardNumber": "5334622382667191",
      "creditCardExpiry": "05/24",
      "cvv": "847"
    }
  },
  {
    "orderNo": "7154BAAA",
    "orderDate": "2023-11-15",
    "orderStatus": "DELIVERED",
    "orderValidationCode": "NO_ERROR",
    "priceTotalInPence": 2600,
    "pizzasInOrder": [
      {
        "name": "R2: Meat Lover",
        "priceInPence": 1400
      },
      {
        "name": "R2: Vegan Delight",
        "priceInPence": 1100
      }
    ],
    "creditCardInformation": {
      "creditCardNumber": "4506929937685528",
      "creditCardExpiry": "06/26",
      "cvv": "305"
    }
  },
  {
    "orderNo": "4541BBCC",
    "orderDate": "2023-11-15",
    "orderStatus": "DELIVERED",
    "orderValidationCode": "NO_ERROR",
    "priceTotalInPence": 2400,
    "pizzasInOrder": [
      {
        "name": "R3: Super Cheese",
        "priceInPence": 1400
      },
      {
        "name": "R3: All Shrooms",
        "priceInPence": 900
      }
    ],
    "creditCardInformation": {
      "creditCardNumber": "5450262940306590",
      "creditCardExpiry": "03/25",
      "cvv": "510"
    }
  },
  {
    "orderNo": "5C4826F2",
    "orderDate": "2023-11-15",
    "orderStatus": "DELIVERED",
    "orderValidationCode": "NO_ERROR",
    "priceTotalInPence": 2400,
    "pizzasInOrder": [
      {
        "name": "R4: Proper Pizza",
        "priceInPence": 1400
      },
      {
        "name": "R4: Pineapple \u0026 Ham \u0026 Cheese",
        "priceInPence": 900
      }
    ],
    "creditCardInformation": {
      "creditCardNumber": "2720253061355376",
      "creditCardExpiry": "11/26",
      "cvv": "463"
    }
  },
  {
    "orderNo": "0E072FC7",
    "orderDate": "2023-11-15",
    "orderStatus": "DELIVERED",
    "orderValidationCode": "NO_ERROR",
    "priceTotalInPence": 2400,
    "pizzasInOrder": [
      {
        "name": "R6: Sucuk delight",
        "priceInPence": 1400
      },
      {
        "name": "R6: Dreams of Syria",
        "priceInPence": 900
      }
    ],
    "creditCardInformation": {
      "creditCardNumber": "5376533118197446",
      "creditCardExpiry": "09/28",
      "cvv": "325"
    }
  },
  {
    "orderNo": "0AF21D5C",
    "orderDate": "2023-11-15",
    "orderStatus": "DELIVERED",
    "orderValidationCode": "NO_ERROR",
    "priceTotalInPence": 2600,
    "pizzasInOrder": [
      {
        "name": "R2: Meat Lover",
        "priceInPence": 1400
      },
      {
        "name": "R2: Vegan Delight",
        "priceInPence": 1100
      }
    ],
    "creditCardInformation": {
      "creditCardNumber": "5594957348063639",
      "creditCardExpiry": "11/28",
      "cvv": "620"
    }
  },
  {
    "orderNo": "6B366B7F",
    "orderDate": "2023-11-15",
    "orderStatus": "DELIVERED",
    "orderValidationCode": "NO_ERROR",
    "priceTotalInPence": 2400,
    "pizzasInOrder": [
      {
        "name": "R3: Super Cheese",
        "priceInPence": 1400
      },
      {
        "name": "R3: All Shrooms",
        "priceInPence": 900
      }
    ],
    "creditCardInformation": {
      "creditCardNumber": "4560605727110777",
      "creditCardExpiry": "08/25",
      "cvv": "600"
    }
  },
  {
    "orderNo": "22E55182",
    "orderDate": "2023-11-15",
    "orderStatus": "DELIVERED",
    "orderValidationCode": "NO_ERROR",
    "priceTotalInPence": 2400,
    "pizzasInOrder": [
      {
        "name": "R4: Proper Pizza",
        "priceInPence": 1400
      },
      {
        "name": "R4: Pineapple \u0026 Ham \u0026 Cheese",
        "priceInPence": 900
      }
    ],
    "creditCardInformation": {
      "creditCardNumber": "5400368151367980",
      "creditCardExpiry": "02/28",
      "cvv": "621"
    }
  },
  {
    "orderNo": "0EC1B001",
    "orderDate": "2023-11-15",
    "orderStatus": "DELIVERED",
    "orderValidationCode": "NO_ERROR",
    "priceTotalInPence": 2400,
    "pizzasInOrder": [
      {
        "name": "R6: Sucuk delight",
        "priceInPence": 1400
      },
      {
        "name": "R6: Dreams of Syria",
        "priceInPence": 900
      }
    ],
    "creditCardInformation": {
      "creditCardNumber": "2720998885589135",
      "creditCardExpiry": "03/24",
      "cvv": "050"
    }
  },
  {
    "orderNo": "2E68C13B",
    "orderDate": "2023-11-15",
    "orderStatus": "DELIVERED",
    "orderValidationCode": "NO_ERROR",
    "priceTotalInPence": 2600,
    "pizzasInOrder": [
      {
        "name": "R2: Meat Lover",
        "priceInPence": 1400
      },
      {
        "name": "R2: Vegan Delight",
        "priceInPence": 1100
      }
    ],
    "creditCardInformation": {
      "creditCardNumber": "4642209965794434",
      "creditCardExpiry": "03/28",
      "cvv": "172"
    }
  },
  {
    "orderNo": "5B74B749",
    "orderDate": "2023-11-15",
    "orderStatus": "DELIVERED",
    "orderValidationCode": "NO_ERROR",
    "priceTotalInPence": 2400,
    "pizzasInOrder": [
      {
        "name": "R3: Super Cheese",
        "priceInPence": 1400
      },
      {
        "name": "R3: All Shrooms",
        "priceInPence": 900
      }
    ],
    "creditCardInformation": {
      "creditCardNumber": "4423831619458093",
      "creditCardExpiry": "01/25",
      "cvv": "923"
    }
  }
]